KCw_WebSurferAgent/__init__.py
KCw_WebSurferAgent/kcw_multimodal_web_surfer.py
KCw_WebSurferAgent/kcw_playwright_controller.py
KCw_WebSurferAgent/kcw_tool_definitions.py
KCw_WebSurferAgent/page_script.js
kcw_websurferagent-0.1.1.dist-info/METADATA
kcw_websurferagent-0.1.1.dist-info/WHEEL
kcw_websurferagent-0.1.1.dist-info/RECORD
