Metadata-Version: 2.4
Name: KCw-WebSurferAgent
Version: 0.1.1
Summary: This is an agent package to automate KCw workflows.
Project-URL: Homepage, https://github.com/kpmg-nl-emu/dani-agent.git
Author-email: Richter van Emmerik <vanemmerik.richter@kpmg.nl>
Classifier: License :: OSI Approved :: MIT License
Classifier: Operating System :: OS Independent
Classifier: Programming Language :: Python :: 3
Requires-Python: >=3.10
Requires-Dist: aiofiles>=24.1.0
Requires-Dist: aiohttp>=3.12.15
Requires-Dist: autogen-agentchat>=0.7.1
Requires-Dist: autogen-core>=0.7.1
Requires-Dist: autogen-ext>=0.7.1
Requires-Dist: azure-ai-inference>=1.0.0b9
Requires-Dist: azure-core>=1.35.0
Requires-Dist: azure-identity>=1.23.1
Requires-Dist: playwright>=1.54.0
Requires-Dist: python-dotenv>=1.1.1
Requires-Dist: requests>=2.32.4
